tsdl/__init__.py
tsdl/testcase.py
tsdl/api/__init__.py
tsdl/api/acc.py
tsdl/api/app.py
tsdl/api/em.py
tsdl/api/mm.py
tsdl/api/pro.py
tsdl/api/req.py
tsdl/api/url.py
tsdl/common/__init__.py
tsdl/common/assist.py
tsdl/common/util.py
tsdl/config/__init__.py
tsdl/config/config.ini
tsdl/config/config.py
tsdl/core/__init__.py
tsdl/core/command.py
tsdl/core/context.py
tsdl/core/interpret.py
tsdl/guide/__init__.py
tsdl/guide/guider.py
tsdl/logger/__init__.py
tsdl/logger/log.py
tsdl-0.4.6.dist-info/LICENSE
tsdl-0.4.6.dist-info/METADATA
tsdl-0.4.6.dist-info/WHEEL
tsdl-0.4.6.dist-info/top_level.txt
tsdl-0.4.6.dist-info/RECORD
