Metadata-Version: 2.1
Name: tsdl
Version: 0.4.6
Summary: Test Script Development Library
Home-page: https://gitee.com/henry9000/tsdl
Author: zhangyue
Author-email: zhangyue@techen.cn
Project-URL: Bug Tracker, https://gitee.com/henry9000/tsdl/issues
Classifier: Programming Language :: Python :: 3
Classifier: License :: OSI Approved :: MIT License
Classifier: Operating System :: OS Independent
Requires-Python: >=3.9
License-File: LICENSE
Requires-Dist: requests
